Workbook

Sheet Assumptions
A1: Unit Economics Model — EdTech Subscription Product
A2: Все синие ячейки — входные допущения (легенда: измени их, модель пересчитается автоматически)
A4: Ключевые допущения
A5: Средний чек за месяц подписки ($) | B5: 25 | C5: Источник: данные пользователя (гипотетический продукт)
A6: Валовая маржа (% от выручки) | B6: 0.72 | C6: Типично для EdTech SaaS: 70-75%
A7: Средний срок жизни подписчика (месяцев) | B7: 5.5 | C7: Рассчитано из retention-кривой проекта 1 (см. лист Cohort_LTV)
A8: Ежемесячный рост базы новых пользователей (%) | B8: 0.04 | C8: Консервативная оценка
A9: Фиксированные операционные расходы в месяц ($) | B9: 18000 | C9: Команда + инфраструктура
A11: CAC по каналам привлечения ($) — из проекта 1 (структура каналов)
A12: Канал | B12: CAC ($) | C12: Completion rate (из проекта 1) | D12: Доля в бюджете
A13: Corporate | B13: 42 | C13: 0.589 | D13: 0.2
A14: Partner referral | B14: 18 | C14: 0.495 | D14: 0.2
A15: Organic | B15: 6 | C15: 0.431 | D15: 0.25
A16: Paid ads | B16: 35 | C16: 0.252 | D16: 0.25
A17: Social media | B17: 22 | C17: 0.231 | D17: 0.1
A19: Blended CAC ($, средневзвешенный по бюджету) | B19: =SUMPRODUCT(B13:B17,D13:D17) -> 24.45

Sheet Cohort_LTV
A1: LTV-модель на основе retention-кривой (проект 1)
A2: Retention % по неделям взят как среднее по 4 когортам из SQL-анализа (result_cohort_retention.csv)
A4: Неделя | B4: Retention % | C4: Активных на 1000 стартовавших | D4: Выручка недели ($)
A5: 0 | B5: 1 | C5: =B5*1000 -> 1000 | D5: =C5*(Assumptions!$B$5/4.33)*Assumptions!$B$6 -> 4157.0439
A6: 1 | B6: 0.906 | C6: =B6*1000 -> 906 | D6: =C6*(Assumptions!$B$5/4.33)*Assumptions!$B$6 -> 3766.2818
A7: 2 | B7: 0.822 | C7: =B7*1000 -> 822 | D7: =C7*(Assumptions!$B$5/4.33)*Assumptions!$B$6 -> 3417.0901
A8: 3 | B8: 0.739 | C8: =B8*1000 -> 739 | D8: =C8*(Assumptions!$B$5/4.33)*Assumptions!$B$6 -> 3072.0554
A9: 4 | B9: 0.665 | C9: =B9*1000 -> 665 | D9: =C9*(Assumptions!$B$5/4.33)*Assumptions!$B$6 -> 2764.4342
A10: 5 | B10: 0.606 | C10: =B10*1000 -> 606 | D10: =C10*(Assumptions!$B$5/4.33)*Assumptions!$B$6 -> 2519.1686
A11: 6 | B11: 0.548 | C11: =B11*1000 -> 548 | D11: =C11*(Assumptions!$B$5/4.33)*Assumptions!$B$6 -> 2278.06
A12: 7 | B12: 0.5 | C12: =B12*1000 -> 500 | D12: =C12*(Assumptions!$B$5/4.33)*Assumptions!$B$6 -> 2078.5219
A13: 8 | B13: 0.46 | C13: =B13*1000 -> 460 | D13: =C13*(Assumptions!$B$5/4.33)*Assumptions!$B$6 -> 1912.2402
A14: 9 | B14: 0.425 | C14: =B14*1000 -> 425 | D14: =C14*(Assumptions!$B$5/4.33)*Assumptions!$B$6 -> 1766.7436
A15: 10 | B15: 0.391 | C15: =B15*1000 -> 391 | D15: =C15*(Assumptions!$B$5/4.33)*Assumptions!$B$6 -> 1625.4042
A16: 11 | B16: 0.36 | C16: =B16*1000 -> 360 | D16: =C16*(Assumptions!$B$5/4.33)*Assumptions!$B$6 -> 1496.5358
A17: 12 | B17: 0.331 | C17: =B17*1000 -> 331 | D17: =C17*(Assumptions!$B$5/4.33)*Assumptions!$B$6 -> 1375.9815
A19: Суммарная выручка (маржинальная) на 1000 стартовавших за 12 недель | D19: =SUM(D5:D17) -> 32229.561
A21: LTV на одного пользователя ($, маржинальный, за период наблюдения) | D21: =D19/1000 -> 32.229561

Sheet Unit_Economics
A1: Unit Economics по каналам: LTV / CAC, payback period
A3: Канал | B3: CAC ($) | C3: LTV ($) | D3: LTV/CAC | E3: Payback (мес.) | F3: Вердикт
A4: =Assumptions!A13 -> Corporate | B4: =Assumptions!B13 -> 42 | C4: =Cohort_LTV!$D$21*(Assumptions!C13/AVERAGE(Assumptions!$C$13:$C$17)) -> 47.505534 | D4: =C4/B4 -> 1.1310842 | E4: =B4/(C4/5.5) -> 4.8625913 | F4: =IF(D4>=3,"Здоровая экономика",IF(D4>=1,"Приемлемо, требует оптимизации","Убыточный канал")) -> Приемлемо, требует оптимизации
A5: =Assumptions!A14 -> Partner referral | B5: =Assumptions!B14 -> 18 | C5: =Cohort_LTV!$D$21*(Assumptions!C14/AVERAGE(Assumptions!$C$13:$C$17)) -> 39.924006 | D5: =C5/B5 -> 2.2180003 | E5: =B5/(C5/5.5) -> 2.4797111 | F5: =IF(D5>=3,"Здоровая экономика",IF(D5>=1,"Приемлемо, требует оптимизации","Убыточный канал")) -> Приемлемо, требует оптимизации
A6: =Assumptions!A15 -> Organic | B6: =Assumptions!B15 -> 6 | C6: =Cohort_LTV!$D$21*(Assumptions!C15/AVERAGE(Assumptions!$C$13:$C$17)) -> 34.762114 | D6: =C6/B6 -> 5.7936857 | E6: =B6/(C6/5.5) -> 0.94930935 | F6: =IF(D6>=3,"Здоровая экономика",IF(D6>=1,"Приемлемо, требует оптимизации","Убыточный канал")) -> Здоровая экономика
A7: =Assumptions!A16 -> Paid ads | B7: =Assumptions!B16 -> 35 | C7: =Cohort_LTV!$D$21*(Assumptions!C16/AVERAGE(Assumptions!$C$13:$C$17)) -> 20.324949 | D7: =C7/B7 -> 0.58071281 | E7: =B7/(C7/5.5) -> 9.4711187 | F7: =IF(D7>=3,"Здоровая экономика",IF(D7>=1,"Приемлемо, требует оптимизации","Убыточный канал")) -> Убыточный канал
A8: =Assumptions!A17 -> Social media | B8: =Assumptions!B17 -> 22 | C8: =Cohort_LTV!$D$21*(Assumptions!C17/AVERAGE(Assumptions!$C$13:$C$17)) -> 18.631203 | D8: =C8/B8 -> 0.84687285 | E8: =B8/(C8/5.5) -> 6.4944814 | F8: =IF(D8>=3,"Здоровая экономика",IF(D8>=1,"Приемлемо, требует оптимизации","Убыточный канал")) -> Убыточный канал
A11: Правило: LTV/CAC >= 3x считается здоровой unit-экономикой для подписочных продуктов.

Sheet Scenario_PnL
A1: Сценарный P&L на 12 месяцев (Base / Optimistic / Pessimistic)
A3: Множитель роста базы (к базовому темпу из Assumptions!B8)
B4: Base | C4: Optimistic | D4: Pessimistic
A5: Growth multiplier | B5: 1 | C5: 1.5 | D5: 0.6
A6: Стартовая база подписчиков (мес. 1) | B6: 2400
A8: Прогноз базы подписчиков (Base сценарий)
A10: Месяц | B10: Base | C10: Optimistic | D10: Pessimistic
A11: 1 | B11: =$B$6 -> 2400 | C11: =$B$6 -> 2400 | D11: =$B$6 -> 2400
A12: 2 | B12: =B11*(1+Assumptions!$B$8*$B$5) -> 2496 | C12: =C11*(1+Assumptions!$B$8*$C$5) -> 2544 | D12: =D11*(1+Assumptions!$B$8*$D$5) -> 2457.6
A13: 3 | B13: =B12*(1+Assumptions!$B$8*$B$5) -> 2595.84 | C13: =C12*(1+Assumptions!$B$8*$C$5) -> 2696.64 | D13: =D12*(1+Assumptions!$B$8*$D$5) -> 2516.5824
A14: 4 | B14: =B13*(1+Assumptions!$B$8*$B$5) -> 2699.6736 | C14: =C13*(1+Assumptions!$B$8*$C$5) -> 2858.4384 | D14: =D13*(1+Assumptions!$B$8*$D$5) -> 2576.9804
A15: 5 | B15: =B14*(1+Assumptions!$B$8*$B$5) -> 2807.6605 | C15: =C14*(1+Assumptions!$B$8*$C$5) -> 3029.9447 | D15: =D14*(1+Assumptions!$B$8*$D$5) -> 2638.8279
A16: 6 | B16: =B15*(1+Assumptions!$B$8*$B$5) -> 2919.967 | C16: =C15*(1+Assumptions!$B$8*$C$5) -> 3211.7414 | D16: =D15*(1+Assumptions!$B$8*$D$5) -> 2702.1598
A17: 7 | B17: =B16*(1+Assumptions!$B$8*$B$5) -> 3036.7656 | C17: =C16*(1+Assumptions!$B$8*$C$5) -> 3404.4459 | D17: =D16*(1+Assumptions!$B$8*$D$5) -> 2767.0116
A18: 8 | B18: =B17*(1+Assumptions!$B$8*$B$5) -> 3158.2363 | C18: =C17*(1+Assumptions!$B$8*$C$5) -> 3608.7126 | D18: =D17*(1+Assumptions!$B$8*$D$5) -> 2833.4199
A19: 9 | B19: =B18*(1+Assumptions!$B$8*$B$5) -> 3284.5657 | C19: =C18*(1+Assumptions!$B$8*$C$5) -> 3825.2354 | D19: =D18*(1+Assumptions!$B$8*$D$5) -> 2901.422
A20: 10 | B20: =B19*(1+Assumptions!$B$8*$B$5) -> 3415.9483 | C20: =C19*(1+Assumptions!$B$8*$C$5) -> 4054.7495 | D20: =D19*(1+Assumptions!$B$8*$D$5) -> 2971.0561
A21: 11 | B21: =B20*(1+Assumptions!$B$8*$B$5) -> 3552.5863 | C21: =C20*(1+Assumptions!$B$8*$C$5) -> 4298.0345 | D21: =D20*(1+Assumptions!$B$8*$D$5) -> 3042.3614
A22: 12 | B22: =B21*(1+Assumptions!$B$8*$B$5) -> 3694.6897 | C22: =C21*(1+Assumptions!$B$8*$C$5) -> 4555.9165 | D22: =D21*(1+Assumptions!$B$8*$D$5) -> 3115.3781
A24: Выручка (маржинальная, $/мес)
A25: Месяц | B25: Base | C25: Optimistic | D25: Pessimistic | E25: EBITDA (Base)
A26: 1 | B26: =B11*Assumptions!$B$5*Assumptions!$B$6 -> 43200 | C26: =C11*Assumptions!$B$5*Assumptions!$B$6 -> 43200 | D26: =D11*Assumptions!$B$5*Assumptions!$B$6 -> 43200 | E26: =B26-Assumptions!$B$9 -> 25200
A27: 2 | B27: =B12*Assumptions!$B$5*Assumptions!$B$6 -> 44928 | C27: =C12*Assumptions!$B$5*Assumptions!$B$6 -> 45792 | D27: =D12*Assumptions!$B$5*Assumptions!$B$6 -> 44236.8 | E27: =B27-Assumptions!$B$9 -> 26928
A28: 3 | B28: =B13*Assumptions!$B$5*Assumptions!$B$6 -> 46725.12 | C28: =C13*Assumptions!$B$5*Assumptions!$B$6 -> 48539.52 | D28: =D13*Assumptions!$B$5*Assumptions!$B$6 -> 45298.483 | E28: =B28-Assumptions!$B$9 -> 28725.12
A29: 4 | B29: =B14*Assumptions!$B$5*Assumptions!$B$6 -> 48594.125 | C29: =C14*Assumptions!$B$5*Assumptions!$B$6 -> 51451.891 | D29: =D14*Assumptions!$B$5*Assumptions!$B$6 -> 46385.647 | E29: =B29-Assumptions!$B$9 -> 30594.125
A30: 5 | B30: =B15*Assumptions!$B$5*Assumptions!$B$6 -> 50537.89 | C30: =C15*Assumptions!$B$5*Assumptions!$B$6 -> 54539.005 | D30: =D15*Assumptions!$B$5*Assumptions!$B$6 -> 47498.902 | E30: =B30-Assumptions!$B$9 -> 32537.89
A31: 6 | B31: =B16*Assumptions!$B$5*Assumptions!$B$6 -> 52559.405 | C31: =C16*Assumptions!$B$5*Assumptions!$B$6 -> 57811.345 | D31: =D16*Assumptions!$B$5*Assumptions!$B$6 -> 48638.876 | E31: =B31-Assumptions!$B$9 -> 34559.405
A32: 7 | B32: =B17*Assumptions!$B$5*Assumptions!$B$6 -> 54661.782 | C32: =C17*Assumptions!$B$5*Assumptions!$B$6 -> 61280.026 | D32: =D17*Assumptions!$B$5*Assumptions!$B$6 -> 49806.209 | E32: =B32-Assumptions!$B$9 -> 36661.782
A33: 8 | B33: =B18*Assumptions!$B$5*Assumptions!$B$6 -> 56848.253 | C33: =C18*Assumptions!$B$5*Assumptions!$B$6 -> 64956.827 | D33: =D18*Assumptions!$B$5*Assumptions!$B$6 -> 51001.558 | E33: =B33-Assumptions!$B$9 -> 38848.253
A34: 9 | B34: =B19*Assumptions!$B$5*Assumptions!$B$6 -> 59122.183 | C34: =C19*Assumptions!$B$5*Assumptions!$B$6 -> 68854.237 | D34: =D19*Assumptions!$B$5*Assumptions!$B$6 -> 52225.595 | E34: =B34-Assumptions!$B$9 -> 41122.183
A35: 10 | B35: =B20*Assumptions!$B$5*Assumptions!$B$6 -> 61487.07 | C35: =C20*Assumptions!$B$5*Assumptions!$B$6 -> 72985.491 | D35: =D20*Assumptions!$B$5*Assumptions!$B$6 -> 53479.01 | E35: =B35-Assumptions!$B$9 -> 43487.07
A36: 11 | B36: =B21*Assumptions!$B$5*Assumptions!$B$6 -> 63946.553 | C36: =C21*Assumptions!$B$5*Assumptions!$B$6 -> 77364.62 | D36: =D21*Assumptions!$B$5*Assumptions!$B$6 -> 54762.506 | E36: =B36-Assumptions!$B$9 -> 45946.553
A37: 12 | B37: =B22*Assumptions!$B$5*Assumptions!$B$6 -> 66504.415 | C37: =C22*Assumptions!$B$5*Assumptions!$B$6 -> 82006.498 | D37: =D22*Assumptions!$B$5*Assumptions!$B$6 -> 56076.806 | E37: =B37-Assumptions!$B$9 -> 48504.415
A39: Итого выручка за 12 мес (Base) | B39: =SUM(B26:B37) -> 649114.8
A40: Итого EBITDA за 12 мес (Base) | B40: =SUM(E26:E37) -> 433114.8
